{
  "minecraft:recipes/building_blocks/cherry_slab": {
    "criteria": {
      "has_planks": "2025-02-15 11:21:43 -0300"
    },
    "done": true
  },
  "minecraft:recipes/redstone/cherry_fence_gate": {
    "criteria": {
      "has_planks": "2025-02-15 11:21:43 -0300"
    },
    "done": true
  },
  "minecraft:recipes/decorations/cherry_sign": {
    "criteria": {
      "has_planks": "2025-02-15 11:21:43 -0300"
    },
    "done": true
  },
  "minecraft:recipes/misc/gold_nugget_from_smelting": {
    "criteria": {
      "has_golden_axe": "2025-02-15 11:30:34 -0300"
    },
    "done": true
  },
  "minecraft:recipes/misc/charcoal": {
    "criteria": {
      "has_log": "2025-02-15 11:20:28 -0300"
    },
    "done": true
  },
  "minecraft:recipes/redstone/cherry_pressure_plate": {
    "criteria": {
      "has_planks": "2025-02-15 11:21:43 -0300"
    },
    "done": true
  },
  "minecraft:recipes/decorations/cherry_fence": {
    "criteria": {
      "has_planks": "2025-02-15 11:21:43 -0300"
    },
    "done": true
  },
  "minecraft:recipes/misc/gold_nugget_from_blasting": {
    "criteria": {
      "has_golden_axe": "2025-02-15 11:30:33 -0300"
    },
    "done": true
  },
  "minecraft:recipes/building_blocks/cherry_stairs": {
    "criteria": {
      "has_planks": "2025-02-15 11:21:43 -0300"
    },
    "done": true
  },
  "minecraft:recipes/decorations/composter": {
    "criteria": {
      "has_wood_slab": "2025-02-15 11:20:46 -0300"
    },
    "done": true
  },
  "minecraft:recipes/decorations/crafting_table": {
    "criteria": {
      "unlock_right_away": "2025-02-15 11:20:28 -0300"
    },
    "done": true
  },
  "minecraft:recipes/misc/stick": {
    "criteria": {
      "has_planks": "2025-02-15 11:21:43 -0300"
    },
    "done": true
  },
  "minecraft:recipes/redstone/cherry_trapdoor": {
    "criteria": {
      "has_planks": "2025-02-15 11:21:43 -0300"
    },
    "done": true
  },
  "minecraft:recipes/redstone/cherry_button": {
    "criteria": {
      "has_planks": "2025-02-15 11:21:43 -0300"
    },
    "done": true
  },
  "minecraft:recipes/building_blocks/cherry_planks": {
    "criteria": {
      "has_log": "2025-02-15 11:20:28 -0300"
    },
    "done": true
  },
  "minecraft:adventure/adventuring_time": {
    "criteria": {
      "minecraft:plains": "2025-02-15 11:20:29 -0300"
    },
    "done": false
  },
  "minecraft:recipes/decorations/barrel": {
    "criteria": {
      "has_wood_slab": "2025-02-15 11:20:46 -0300"
    },
    "done": true
  },
  "minecraft:recipes/redstone/cherry_door": {
    "criteria": {
      "has_planks": "2025-02-15 11:21:43 -0300"
    },
    "done": true
  },
  "DataVersion": 3955
}